PySink/AsyncManager.py
PySink/AsyncWorker.py
PySink/CancellableAsyncWorker.py
PySink/__init__.py
PySink/Objects/AsyncWorkerProgress.py
PySink/Objects/AsyncWorkerResults.py
PySink/Objects/AsyncWorkerSignals.py
PySink/Objects/__init__.py
PySink/Widgets/ProgressBarWidget.py
PySink/Widgets/__init__.py
PySink-0.0.10.dist-info/LICENSE
PySink-0.0.10.dist-info/METADATA
PySink-0.0.10.dist-info/WHEEL
PySink-0.0.10.dist-info/top_level.txt
PySink-0.0.10.dist-info/RECORD
