Metadata-Version: 2.1
Name: PySink
Version: 0.0.10
Summary: PySide6 Helpers for Powerful Async Desktop Apps
Author-email: Zack Johnson <zackjohnson298@gmail.com>
License: MIT License
Keywords: python,app,gui,async,application,desktop,ui
Classifier: Development Status :: 1 - Planning
Classifier: Intended Audience :: Developers
Classifier: Programming Language :: Python :: 3
Classifier: Operating System :: Unix
Classifier: Operating System :: MacOS :: MacOS X
Classifier: Operating System :: Microsoft :: Windows
Requires-Python: >=3.9
License-File: LICENSE
Requires-Dist: PySide6
